datasette_publish_azure/__init__.py
datasette_publish_azure-0.1a0.dist-info/METADATA
datasette_publish_azure-0.1a0.dist-info/WHEEL
datasette_publish_azure-0.1a0.dist-info/entry_points.txt
datasette_publish_azure-0.1a0.dist-info/top_level.txt
datasette_publish_azure-0.1a0.dist-info/RECORD
