Metadata-Version: 2.1
Name: datasette-publish-azure
Version: 0.1a0
Summary: Publish Datasette instances to Azure Functions
Home-page: https://github.com/simonw/datasette-publish-azure
Author: Simon Willison
License: Apache License, Version 2.0
Project-URL: Issues, https://github.com/simonw/datasette-publish-azure/issues
Project-URL: CI, https://github.com/simonw/datasette-publish-azure/actions
Project-URL: Changelog, https://github.com/simonw/datasette-publish-azure/releases
Platform: UNKNOWN
Requires-Python: >=3.6
Requires-Dist: datasette
Provides-Extra: test
Requires-Dist: pytest ; extra == 'test'
Requires-Dist: pytest-asyncio ; extra == 'test'
